ryzenai_dynamic_dispatch/__init__.py
ryzenai_dynamic_dispatch-1.1.0.dev1.dist-info/licenses/LICENSE.txt
ryzenai_dynamic_dispatch-1.1.0.dev1.dist-info/METADATA
ryzenai_dynamic_dispatch-1.1.0.dev1.dist-info/WHEEL
ryzenai_dynamic_dispatch-1.1.0.dev1.dist-info/RECORD
